skill_mcp_server/__init__.py
skill_mcp_server/__main__.py
skill_mcp_server/config/__init__.py
skill_mcp_server/config/defaults.py
skill_mcp_server/config/loader.py
skill_mcp_server/config/settings.py
skill_mcp_server/core/__init__.py
skill_mcp_server/core/exceptions.py
skill_mcp_server/core/registry.py
skill_mcp_server/core/server.py
skill_mcp_server/executor/__init__.py
skill_mcp_server/executor/base.py
skill_mcp_server/executor/factory.py
skill_mcp_server/executor/node.py
skill_mcp_server/executor/python.py
skill_mcp_server/executor/shell.py
skill_mcp_server/security/__init__.py
skill_mcp_server/security/file_validator.py
skill_mcp_server/security/path_validator.py
skill_mcp_server/skill/__init__.py
skill_mcp_server/skill/manager.py
skill_mcp_server/skill/models.py
skill_mcp_server/skill/parser.py
skill_mcp_server/skill/scanner.py
skill_mcp_server/tools/__init__.py
skill_mcp_server/tools/base.py
skill_mcp_server/tools/file_editor.py
skill_mcp_server/tools/file_reader.py
skill_mcp_server/tools/file_writer.py
skill_mcp_server/tools/resource_reader.py
skill_mcp_server/tools/script_executor.py
skill_mcp_server/tools/skill_lister.py
skill_mcp_server/tools/skill_loader.py
skill_mcp_server/utils/__init__.py
skill_mcp_server/utils/frontmatter.py
skill_mcp_server/utils/logging.py
skill_mcp_server/utils/markdown.py
skill_mcp_server-0.1.0.dist-info/METADATA
skill_mcp_server-0.1.0.dist-info/WHEEL
skill_mcp_server-0.1.0.dist-info/entry_points.txt
skill_mcp_server-0.1.0.dist-info/licenses/LICENSE
skill_mcp_server-0.1.0.dist-info/RECORD
