Metadata-Version: 2.4
Name: skill-mcp-server
Version: 0.1.0
Summary: Turn any AI agent into a specialist - A Model Context Protocol server for modular skills
Project-URL: Homepage, https://github.com/ephemeraldew/skill_mcp
Project-URL: Documentation, https://github.com/ephemeraldew/skill_mcp#readme
Project-URL: Repository, https://github.com/ephemeraldew/skill_mcp
Project-URL: Issues, https://github.com/ephemeraldew/skill_mcp/issues
Project-URL: Changelog, https://github.com/ephemeraldew/skill_mcp/blob/main/CHANGELOG.md
Author-email: ephemeraldew <ephemeraldew@users.noreply.github.com>
License-Expression: MIT
License-File: LICENSE
Keywords: agent,ai,automation,claude,llm,mcp,model-context-protocol,skills
Classifier: Development Status :: 4 - Beta
Classifier: Intended Audience :: Developers
Classifier: License :: OSI Approved :: MIT License
Classifier: Operating System :: OS Independent
Classifier: Programming Language :: Python :: 3
Classifier: Programming Language :: Python :: 3.10
Classifier: Programming Language :: Python :: 3.11
Classifier: Programming Language :: Python :: 3.12
Classifier: Topic :: Scientific/Engineering :: Artificial Intelligence
Classifier: Topic :: Software Development :: Libraries :: Python Modules
Requires-Python: >=3.10
Requires-Dist: mcp>=1.0.0
Provides-Extra: dev
Requires-Dist: mypy>=1.5.0; extra == 'dev'
Requires-Dist: pytest-asyncio>=0.21.0; extra == 'dev'
Requires-Dist: pytest-cov>=4.1.0; extra == 'dev'
Requires-Dist: pytest>=7.4.0; extra == 'dev'
Requires-Dist: ruff>=0.1.0; extra == 'dev'
